supercell_step/__init__.py
supercell_step/_version.py
supercell_step/supercell.py
supercell_step/supercell_parameters.py
supercell_step/supercell_step.py
supercell_step/tk_supercell.py
supercell_step-2025.6.25.1.dist-info/licenses/AUTHORS.rst
supercell_step-2025.6.25.1.dist-info/licenses/LICENSE
supercell_step-2025.6.25.1.dist-info/METADATA
supercell_step-2025.6.25.1.dist-info/WHEEL
supercell_step-2025.6.25.1.dist-info/entry_points.txt
supercell_step-2025.6.25.1.dist-info/top_level.txt
supercell_step-2025.6.25.1.dist-info/zip-safe
supercell_step-2025.6.25.1.dist-info/RECORD
